{
  "name": "Batter App Local",
  "values": [
    { "key": "baseUrl", "value": "http://localhost:5000", "enabled": true },
    { "key": "phone", "value": "9999999999", "enabled": true },
    { "key": "otp", "value": "", "enabled": true },
    { "key": "token", "value": "", "enabled": true },
    { "key": "addressText", "value": "12 OMR Road", "enabled": true },
    { "key": "landmark", "value": "Near Tech Park", "enabled": true },
    { "key": "lat", "value": "12.9123", "enabled": true },
    { "key": "lng", "value": "80.1987", "enabled": true },
    { "key": "zoneId", "value": "", "enabled": true },
    { "key": "productId", "value": "", "enabled": true },
    { "key": "slotId", "value": "", "enabled": true },
    { "key": "orderId", "value": "", "enabled": true },
    { "key": "date", "value": "2026-02-14", "enabled": true },
    { "key": "quantity", "value": "2", "enabled": true }
  ],
  "_postman_variable_scope": "environment",
  "_postman_exported_at": "2026-02-14T00:00:00.000Z",
  "_postman_exported_using": "Postman/10"
}
